liketext/__init__.py
liketext/re.py
liketext/text.py
liketext/text_decorations.py
liketext-1.1.dist-info/METADATA
liketext-1.1.dist-info/WHEEL
liketext-1.1.dist-info/licenses/LICENSE
liketext-1.1.dist-info/RECORD
